cicd_tools/__init__.py
cicd_tools/cli.py
cicd_tools/menus/__init__.py
cicd_tools/menus/app_menu.py
cicd_tools/menus/create_menu.py
cicd_tools/menus/menu_utils.py
cicd_tools/project_templates/__init__.py
cicd_tools/project_templates/development_project/.bumpversion.cfg.jinja
cicd_tools/project_templates/development_project/.gitignore.jinja
cicd_tools/project_templates/development_project/.pre-commit-config.yaml.jinja
cicd_tools/project_templates/development_project/Dockerfile.jinja
cicd_tools/project_templates/development_project/LICENSE.jinja
cicd_tools/project_templates/development_project/README.md.jinja
cicd_tools/project_templates/development_project/copier.yaml
cicd_tools/project_templates/development_project/docker-compose.yml.jinja
cicd_tools/project_templates/development_project/pyproject.toml.jinja
cicd_tools/project_templates/development_project/.github/workflows/deploy.yml.jinja
cicd_tools/project_templates/development_project/.github/workflows/pytest.yml.jinja
cicd_tools/project_templates/development_project/.github/workflows/release.yml.jinja
cicd_tools/project_templates/development_project/tests/__init__.py.jinja
cicd_tools/project_templates/development_project/tests/test_main.py.jinja
"cicd_tools/project_templates/development_project/{{project_name.replace('-', '_')}}_module/__init__.py.jinja"
"cicd_tools/project_templates/development_project/{{project_name.replace('-', '_')}}_module/main.py.jinja"
cicd_tools/project_templates/simple_project/.gitignore.jinja
cicd_tools/project_templates/simple_project/LICENSE.jinja
cicd_tools/project_templates/simple_project/README.md.jinja
cicd_tools/project_templates/simple_project/copier.yaml
cicd_tools/project_templates/simple_project/setup.py.jinja
cicd_tools/project_templates/simple_project/tests/__init__.py.jinja
cicd_tools/project_templates/simple_project/tests/test_main.py.jinja
"cicd_tools/project_templates/simple_project/{{project_name.replace('-', '_')}}_module/__init__.py.jinja"
cicd_tools-2.0.0.dist-info/METADATA
cicd_tools-2.0.0.dist-info/WHEEL
cicd_tools-2.0.0.dist-info/entry_points.txt
cicd_tools-2.0.0.dist-info/top_level.txt
cicd_tools-2.0.0.dist-info/RECORD
